spacexpy/__init__.py
spacexpy/spacex.py
spacexpy/spacexerror.py
spacexpy/spacexhttp.py
spacexpy/spacexmodel.py
spacexpy/spacexrequester.py
spacexpy-2.0.2.dist-info/LICENSE
spacexpy-2.0.2.dist-info/METADATA
spacexpy-2.0.2.dist-info/WHEEL
spacexpy-2.0.2.dist-info/top_level.txt
spacexpy-2.0.2.dist-info/RECORD
