Metadata-Version: 2.1
Name: spacexpy
Version: 2.0.2
Summary: SpaceX REST API wrapping with aiohttp
Home-page: https://github.com/SaidBySolo/SpaceX-SimpleWrapper
Author: Ryu ju heon
Author-email: SaidBySolo@gmail.com
License: MIT
Platform: UNKNOWN
Classifier: Programming Language :: Python :: 3.8
Classifier: License :: OSI Approved :: MIT License
Classifier: Operating System :: OS Independent
Requires-Python: >=3.6
License-File: LICENSE
Requires-Dist: aiohttp[speedup]
